multicycle_subset/memory.sv
module synchronous_memory #(
    parameter ADDR_WIDTH = 12,
    parameter WORD_SIZE = 64
)(
    input logic clk,
    input logic reset,
    input logic read_enable,
    input logic write_enable,
    input logic [ADDR_WIDTH - 1 : 0] addr,
    input logic [WORD_SIZE - 1 : 0] write_data,
    output logic [WORD_SIZE - 1 : 0] read_data
);

localparam NUM_WORDS = 1 << ADDR_WIDTH;
logic [WORD_SIZE - 1 : 0] memory [0 : NUM_WORDS - 1];

integer i;
always_ff @(posedge clk) begin
    if (reset) begin
        for (i = 0; i < 1 << ADDR_WIDTH - 1; i = i + 1) begin
            memory[i] <= {{WORD_SIZE}{1'b0}};
        end
    end
    
    else begin
        if (write_enable) begin
            memory[addr] <= write_data;
        end
        if (read_enable) begin
            read_data <= memory[addr];
        end
    end
end

endmodule

multicycle_subset/registers.sv
module riscv_regfile (
    input logic clk,
    input logic reset,
    input logic write_enable,
    input logic [63:0] write_data,
    input logic [4:0] write_addr,
    input logic [4:0] read_addr1,
    input logic [4:0] read_addr2,
    output logic [63:0] read_port1,
    output logic [63:0] read_port2
);

logic [63:0] data [0:31];
logic write_addr_nonzero, read_addr1_nonzero, read_addr2_nonzero;

always_comb begin
    write_addr_nonzero = |write_addr;
    read_addr1_nonzero = |read_addr1;
    read_addr2_nonzero = |read_addr2;
end

integer i;

always_ff @(posedge clk) begin
    if (reset) begin
        for (i = 0; i < 32; i = i + 1) begin
            data[i] <= 64'b0;
        end
    end
    else begin
        if (write_enable && write_addr_nonzero) begin
            data[write_addr] <= write_data;
        end

        read_port1 <= data[read_addr1] & {64{read_addr1_nonzero}};
        read_port2 <= data[read_addr2] & {64{read_addr2_nonzero}};
    end
end

endmodule

module packed_dff #(
    parameter WORD_SIZE = 64
)(
    input logic clk,
    input logic reset,
    input logic write_enable,
    input logic [WORD_SIZE - 1 : 0] write_data,
    output logic [WORD_SIZE - 1 : 0] stored_data
);

always_ff @(posedge clk) begin
    if (reset) begin
        stored_data <= {(WORD_SIZE){1'b0}};
    end
    else if (write_enable) begin
        stored_data <= write_data;
    end
end

endmodule

pipeline/alu.sv
module alu_64 (
    input logic [63:0] operand_1,
    input logic [63:0] operand_2,
    input logic [3:0] opcode,
    output logic [63:0] result,
    output logic zero_flag
);

assign zero_flag = ~(|result);

always_comb begin
    result = 64'b0;

    case (opcode)
        4'b0000:
            result = operand_1 & operand_2;
        4'b0001:
            result = operand_1 | operand_2;
        4'b0010:
            result = operand_1 + operand_2;
        4'b0110:
            result = operand_1 - operand_2;
    endcase
end

endmodule

multicycle_subset/control.sv
module imm_sign_extend #(
    parameter IMM_WIDTH_IN = 12,
    parameter IMM_WIDTH_OUT = 64
)(
    input logic [IMM_WIDTH_IN - 1 : 0] imm_in,
    output logic [IMM_WIDTH_OUT - 1 : 0] imm_out
);

assign imm_out = {
    {(IMM_WIDTH_OUT - IMM_WIDTH_IN){imm_in[IMM_WIDTH_IN - 1]}}, 
    imm_in};

endmodule

module riscv_subset_decoder (
    input logic [31:0] instr,
    output logic reg_write,
    output logic [4:0] reg_waddr,
    output logic [4:0] reg_raddr1,
    output logic [4:0] reg_raddr2,
    output logic use_imm_in_alu,
    output logic [63:0] imm,
    output logic [3:0] alu_opcode,
    output logic dmem_read,
    output logic dmem_write,
    output logic load_instr,
    output logic branch,
    output logic illegal
);

logic [6:0] opcode;
logic [2:0] funct3;
logic [6:0] funct7;

assign opcode = instr[6:0];
assign funct3 = instr[14:12];
assign funct7 = instr[31:25];

logic [11:0] imm12;
logic [12:0] imm13;
logic [63:0] imm_mem;
logic [63:0] imm_b;

imm_sign_extend #(
    .IMM_WIDTH_IN(12),
    .IMM_WIDTH_OUT(64)
) imm_extender_mem (
    .imm_in(imm12),
    .imm_out(imm_mem)
);

imm_sign_extend #(
    .IMM_WIDTH_IN(13),
    .IMM_WIDTH_OUT(64)
) imm_extender_b (
    .imm_in(imm13),
    .imm_out(imm_b)
);

assign reg_waddr = instr[11:7];
assign reg_raddr1 = instr[19:15];
assign reg_raddr2 = instr[24:20];

always_comb begin
    reg_write = 1'b0;
    use_imm_in_alu = 1'b0;
    imm12 = 12'b0;
    imm13 = 13'b0;
    imm = 64'b0;
    alu_opcode = 4'b0;
    dmem_read = 1'b0;
    dmem_write = 1'b0;
    load_instr = 1'b0;
    branch = 1'b0;
    illegal = 1'b1;

    case (opcode)
        //ld
        7'b0000011: begin
            if (funct3 == 3'b011) begin
                reg_write = 1'b1;
                use_imm_in_alu = 1'b1;
                imm12 = instr[31:20];
                imm = imm_mem;
                alu_opcode = 4'b0010;
                dmem_read = 1'b1;
                load_instr = 1'b1;
                illegal = 1'b0;
            end
        end
        //sd
        7'b0100011: begin
            if (funct3 == 3'b011) begin
                use_imm_in_alu = 1'b1;
                imm12 = {instr[31:25], instr[11:7]};
                imm = imm_mem;
                alu_opcode = 4'b0010;
                dmem_write = 1'b1;
                illegal = 1'b0;
            end
        end
        //beq
        7'b1100011: begin
            if (funct3 == 3'b000) begin
                alu_opcode = 4'b0110;
                branch = 1'b1;
                imm13 = {
                    instr[31],
                    instr[7],
                    instr[30:25],
                    instr[11:8],
                    1'b0
                };
                imm = imm_b;
                illegal = 1'b0;
            end
        end
        //arith: and, or, add, sub
        7'b0110011: begin
            case ({funct7, funct3})
                10'b0000000111: begin
                    reg_write = 1'b1;
                    alu_opcode = 4'b0;
                    illegal = 1'b0;
                end
                10'b0000000110: begin
                    reg_write = 1'b1;
                    alu_opcode = 4'b0001;
                    illegal = 1'b0;
                end
                10'b0000000000: begin
                    reg_write = 1'b1;
                    alu_opcode = 4'b0010;
                    illegal = 1'b0;
                end
                10'b0110000000: begin
                    reg_write = 1'b1;
                    alu_opcode = 4'b0110;
                    illegal = 1'b0;
                end
            endcase
        end
        //immediate arithmetic: andi, ori, addi
        7'b0010011: begin
            case (funct3)
                3'b111: begin
                    reg_write = 1'b1;
                    alu_opcode = 4'b0;
                    use_imm_in_alu = 1'b1;
                    imm12 = instr[31:20];
                    imm = imm_mem;
                    illegal = 1'b0;
                end
                3'b110: begin
                    reg_write = 1'b1;
                    alu_opcode = 4'b0001;
                    use_imm_in_alu = 1'b1;
                    imm12 = instr[31:20];
                    imm = imm_mem;
                    illegal = 1'b0;
                end
                3'b000: begin
                    reg_write = 1'b1;
                    alu_opcode = 4'b0010;
                    use_imm_in_alu = 1'b1;
                    imm12 = instr[31:20];
                    imm = imm_mem;
                    illegal = 1'b0;
                end
            endcase
        end
    endcase
end

endmodule

multicycle_subset/core.sv
module riscv64_subset_core_multicycle (
    input logic clk,
    input logic reset,
    input logic [31:0] instr, // Loaded on IF -> ID edge
    output logic [63:0] imem_addr,
    input logic [63:0] dmem_fetch, // A synchronized data memory module will load the correct value of data memory on an ld instruction on EX -> MEM edge.
    output logic dmem_read,
    output logic dmem_write,
    output logic [63:0] dmem_addr,
    output logic [63:0] dmem_data
);

enum {
    IF, ID, EX, MEM, WB
} processor_state;

// ID phase

logic reg_write_dec;
logic [4:0] reg_waddr;
logic [4:0] reg_raddr1;
logic [4:0] reg_raddr2;
logic use_imm_in_alu;
logic [63:0] imm;
logic [3:0] alu_opcode;
logic dmem_read_dec;
logic dmem_write_dec;
logic load_instr;
logic branch;
logic illegal;

riscv_subset_decoder instr_decoder (
    .instr(instr),
    .reg_write(reg_write_dec),
    .reg_waddr(reg_waddr),
    .reg_raddr1(reg_raddr1),
    .reg_raddr2(reg_raddr2),
    .use_imm_in_alu(use_imm_in_alu),
    .imm(imm),
    .alu_opcode(alu_opcode),
    .dmem_read(dmem_read_dec),
    .dmem_write(dmem_write_dec),
    .load_instr(load_instr),
    .branch(branch),
    .illegal(illegal)
);

logic reg_write;
assign reg_write = reg_write_dec & (processor_state == WB);
assign dmem_read = dmem_read_dec & (processor_state == MEM);
assign dmem_write = dmem_write_dec & (processor_state == MEM);

logic [63:0] reg_wdata;
logic [63:0] reg_rdata1;
logic [63:0] reg_rdata2; // Loaded on ID -> EX edge
logic [63:0] alu_input2;

// ID/EX

riscv_regfile regfile (
    .clk(clk),
    .reset(reset),
    .write_enable(reg_write),
    .write_data(reg_wdata),
    .write_addr(reg_waddr),
    .read_addr1(reg_raddr1),
    .read_addr2(reg_raddr2),
    .read_port1(reg_rdata1), // Regfile output ports
    .read_port2(reg_rdata2)
);

// EX phase

logic zero_flag; // Used for branching
logic [63:0] alu_result;

always_comb begin
    if (use_imm_in_alu)
        alu_input2 = imm;
    else
        alu_input2 = reg_rdata2;
end

alu_64 alu (
    .operand_1(reg_rdata1),
    .operand_2(alu_input2),
    .opcode(alu_opcode),
    .result(alu_result),
    .zero_flag(zero_flag)
);

// EX/MEM

packed_dff #(
    .WORD_SIZE(64)
) alu_result_dff_ex_mem (
    .clk(clk),
    .reset(reset),
    .write_enable(1'b1),
    .write_data(alu_result),
    .stored_data(dmem_addr)
);

packed_dff #(
    .WORD_SIZE(64)
) reg_rdata2_dff_ex_mem (
    .clk(clk),
    .reset(reset),
    .write_enable(1'b1),
    .write_data(reg_rdata2),
    .stored_data(dmem_data)
);

// MEM will be handled by the external memory module.

// MEM/WB

logic [63:0] alu_result_wb;

packed_dff #(
    .WORD_SIZE(64)
) alu_result_dff_mem_wb (
    .clk(clk),
    .reset(reset),
    .write_enable(1'b1),
    .write_data(dmem_addr),
    .stored_data(alu_result_wb)
);

// WB phase
always_comb begin
    if (load_instr)
        reg_wdata = dmem_fetch;
    else
        reg_wdata = alu_result_wb;
end

logic [63:0] instr_addr; // PC will update on WB -> IF edge.
logic [63:0] next_instr_addr;
assign imem_addr = instr_addr;

always_comb begin
    if (branch & zero_flag)
        next_instr_addr = instr_addr + imm;
    else
        next_instr_addr = instr_addr + 64'd4;
end

always_ff @(posedge clk) begin
    if (reset) begin
        processor_state <= IF;
        instr_addr <= 64'b0;
    end
    else begin
        case (processor_state)
            IF: processor_state <= ID;
            ID: processor_state <= EX;
            EX: processor_state <= MEM;
            MEM: processor_state <= WB;
            WB: begin
                processor_state <= IF;
                instr_addr <= next_instr_addr;
            end
        endcase
    end
end

endmodule

multicycle_subset/core_tb.sv
`timescale 1ns/1ps

module riscv64_subset_core_multicycle_tb;

logic clk;
logic reset;

logic [31:0] instr;
logic [63:0] imem_addr;

logic [63:0] dmem_fetch;
logic        dmem_read;
logic        dmem_write;
logic [63:0] dmem_addr;
logic [63:0] dmem_data;

riscv64_subset_core_multicycle dut (
    .clk        (clk),
    .reset      (reset),

    .instr      (instr),
    .imem_addr  (imem_addr),

    .dmem_fetch (dmem_fetch),
    .dmem_read  (dmem_read),
    .dmem_write (dmem_write),
    .dmem_addr  (dmem_addr),
    .dmem_data  (dmem_data)
);

synchronous_memory #(
    .ADDR_WIDTH(12),
    .WORD_SIZE(32)
) instr_memory (
    .clk(clk),
    .reset(reset),
    .read_enable(1'b1),
    .write_enable(1'b0),
    .addr(imem_addr[13:2]),
    .write_data(32'b0),
    .read_data(instr)
);

synchronous_memory #(
    .ADDR_WIDTH(12),
    .WORD_SIZE(64)
) data_memory (
    .clk(clk),
    .reset(reset),
    .read_enable(dmem_read),
    .write_enable(dmem_write),
    .addr(dmem_addr[14:3]),
    .write_data(dmem_data),
    .read_data(dmem_fetch)
);

initial begin
    clk = 1'b0;

    forever begin
        #5;
        clk = ~clk;
    end
end

initial begin
    $dumpfile("dump.vcd");
    $dumpvars(0, riscv64_subset_core_multicycle_tb);
end

initial begin
    reset = 1'b1;
    #12;
    reset = 1'b0;
end

initial begin
    // addi x1, x0, 16
    #13;
    instr_memory.memory[0] = {
        12'b000000010000,
        5'b00000,
        3'b000,
        5'b00001,
        7'b0010011
    };

    // addi x2, x0, 48
    instr_memory.memory[1] = {
        12'b000000110000,
        5'b00000,
        3'b000,
        5'b00010,
        7'b0010011
    };

    // sub x3, x2, x1
    instr_memory.memory[2] = {
        7'b0110000,
        5'b00001,
        5'b00010,
        3'b000,
        5'b00011,
        7'b0110011
    };

    // sd x3, 8(x2)
    instr_memory.memory[3] = {
        7'b0000000,
        5'b00011,
        5'b00010,
        3'b011,
        5'b01000,
        7'b0100011
    };

    // ld, x4, 40(x1)
    instr_memory.memory[4] = {
        12'b000000101000,
        5'b00001,
        3'b011,
        5'b00100,
        7'b0000011
    };

    // beq x0, x0, -20
    instr_memory.memory[5] = {
        7'b1111111,
        5'b00000,
        5'b00000,
        3'b000,
        5'b01101,
        7'b1100011
    };
end

always @(posedge clk) begin
    $display(
        "time=%0t PC=%0d state=%0d x1=%0d x2=%0d x3=%0d x4=%0d ALU=%0d",
        $time,
        imem_addr,
        dut.processor_state,
        dut.regfile.data[1],
        dut.regfile.data[2],
        dut.regfile.data[3],
        dut.regfile.data[4],
        dut.alu_result
    );
end

initial begin
    repeat (150) @(posedge clk);
    #1;
    $finish;
end

endmodule

multicycle_subset/dump.vcd
$date
	Thu Sep  3 16:02:16 2026
$end
$version
	Icarus Verilog
$end
$timescale
	1ps
$end
$scope module riscv64_subset_core_multicycle_tb $end
$var wire 32 ! instr [31:0] $end
$var wire 64 " imem_addr [63:0] $end
$var wire 1 # dmem_write $end
$var wire 1 $ dmem_read $end
$var wire 64 % dmem_fetch [63:0] $end
$var wire 64 & dmem_data [63:0] $end
$var wire 64 ' dmem_addr [63:0] $end
$var reg 1 ( clk $end
$var reg 1 ) reset $end
$scope module data_memory $end
$var wire 12 * addr [11:0] $end
$var wire 1 ( clk $end
$var wire 1 ) reset $end
$var wire 1 # write_enable $end
$var wire 64 + write_data [63:0] $end
$var wire 1 $ read_enable $end
$var parameter 32 , ADDR_WIDTH $end
$var parameter 44 - NUM_WORDS $end
$var parameter 32 . WORD_SIZE $end
$var reg 64 / read_data [63:0] $end
$var integer 32 0 i [31:0] $end
$upscope $end
$scope module dut $end
$var wire 1 ( clk $end
$var wire 64 1 dmem_fetch [63:0] $end
$var wire 1 $ dmem_read $end
$var wire 1 # dmem_write $end
$var wire 1 2 reg_write $end
$var wire 1 ) reset $end
$var wire 1 3 zero_flag $end
$var wire 1 4 use_imm_in_alu $end
$var wire 1 5 reg_write_dec $end
$var wire 5 6 reg_waddr [4:0] $end
$var wire 64 7 reg_rdata2 [63:0] $end
$var wire 64 8 reg_rdata1 [63:0] $end
$var wire 5 9 reg_raddr2 [4:0] $end
$var wire 5 : reg_raddr1 [4:0] $end
$var wire 1 ; load_instr $end
$var wire 32 < instr [31:0] $end
$var wire 64 = imm [63:0] $end
$var wire 64 > imem_addr [63:0] $end
$var wire 1 ? illegal $end
$var wire 1 @ dmem_write_dec $end
$var wire 1 A dmem_read_dec $end
$var wire 64 B dmem_data [63:0] $end
$var wire 64 C dmem_addr [63:0] $end
$var wire 1 D branch $end
$var wire 64 E alu_result_wb [63:0] $end
$var wire 64 F alu_result [63:0] $end
$var wire 4 G alu_opcode [3:0] $end
$var reg 64 H alu_input2 [63:0] $end
$var reg 64 I instr_addr [63:0] $end
$var reg 64 J next_instr_addr [63:0] $end
$var reg 64 K reg_wdata [63:0] $end
$var integer 32 L processor_state [31:0] $end
$scope module alu $end
$var wire 64 M operand_2 [63:0] $end
$var wire 1 3 zero_flag $end
$var wire 64 N operand_1 [63:0] $end
$var wire 4 O opcode [3:0] $end
$var reg 64 P result [63:0] $end
$upscope $end
$scope module alu_result_dff_ex_mem $end
$var wire 1 ( clk $end
$var wire 1 ) reset $end
$var wire 64 Q write_data [63:0] $end
$var wire 1 R write_enable $end
$var parameter 32 S WORD_SIZE $end
$var reg 64 T stored_data [63:0] $end
$upscope $end
$scope module alu_result_dff_mem_wb $end
$var wire 1 ( clk $end
$var wire 1 ) reset $end
$var wire 64 U write_data [63:0] $end
$var wire 1 V write_enable $end
$var parameter 32 W WORD_SIZE $end
$var reg 64 X stored_data [63:0] $end
$upscope $end
$scope module instr_decoder $end
$var wire 5 Y reg_waddr [4:0] $end
$var wire 5 Z reg_raddr2 [4:0] $end
$var wire 5 [ reg_raddr1 [4:0] $end
$var wire 7 \ opcode [6:0] $end
$var wire 32 ] instr [31:0] $end
$var wire 64 ^ imm_mem [63:0] $end
$var wire 64 _ imm_b [63:0] $end
$var wire 7 ` funct7 [6:0] $end
$var wire 3 a funct3 [2:0] $end
$var reg 4 b alu_opcode [3:0] $end
$var reg 1 D branch $end
$var reg 1 A dmem_read $end
$var reg 1 @ dmem_write $end
$var reg 1 ? illegal $end
$var reg 64 c imm [63:0] $end
$var reg 12 d imm12 [11:0] $end
$var reg 13 e imm13 [12:0] $end
$var reg 1 ; load_instr $end
$var reg 1 5 reg_write $end
$var reg 1 4 use_imm_in_alu $end
$scope module imm_extender_b $end
$var wire 13 f imm_in [12:0] $end
$var wire 64 g imm_out [63:0] $end
$var parameter 32 h IMM_WIDTH_IN $end
$var parameter 32 i IMM_WIDTH_OUT $end
$upscope $end
$scope module imm_extender_mem $end
$var wire 12 j imm_in [11:0] $end
$var wire 64 k imm_out [63:0] $end
$var parameter 32 l IMM_WIDTH_IN $end
$var parameter 32 m IMM_WIDTH_OUT $end
$upscope $end
$upscope $end
$scope module reg_rdata2_dff_ex_mem $end
$var wire 1 ( clk $end
$var wire 1 ) reset $end
$var wire 1 n write_enable $end
$var wire 64 o write_data [63:0] $end
$var parameter 32 p WORD_SIZE $end
$var reg 64 q stored_data [63:0] $end
$upscope $end
$scope module regfile $end
$var wire 1 ( clk $end
$var wire 5 r read_addr1 [4:0] $end
$var wire 5 s read_addr2 [4:0] $end
$var wire 1 ) reset $end
$var wire 5 t write_addr [4:0] $end
$var wire 64 u write_data [63:0] $end
$var wire 1 2 write_enable $end
$var reg 1 v read_addr1_nonzero $end
$var reg 1 w read_addr2_nonzero $end
$var reg 64 x read_port1 [63:0] $end
$var reg 64 y read_port2 [63:0] $end
$var reg 1 z write_addr_nonzero $end
$var integer 32 { i [31:0] $end
$upscope $end
$upscope $end
$scope module instr_memory $end
$var wire 12 | addr [11:0] $end
$var wire 1 ( clk $end
$var wire 1 } read_enable $end
$var wire 1 ) reset $end
$var wire 32 ~ write_data [31:0] $end
$var wire 1 !" write_enable $end
$var parameter 32 "" ADDR_WIDTH $end
$var parameter 44 #" NUM_WORDS $end
$var parameter 32 $" WORD_SIZE $end
$var reg 32 %" read_data [31:0] $end
$var integer 32 &" i [31:0] $end
$upscope $end
$upscope $end
$enddefinitions $end
$comment Show the parameter values. $end
$dumpall
b100000 $"
b1000000000000 #"
b1100 ""
b1000000 p
b1000000 m
b1100 l
b1000000 i
b1101 h
b1000000 W
b1000000 S
b1000000 .
b1000000000000 -
b1100 ,
$end
#0
$dumpvars
bx &"
bx %"
0!"
b0 ~
1}
bx |
bx {
xz
bx y
bx x
xw
xv
bx u
bx t
bx s
bx r
bx q
bx o
1n
b0 k
b0 j
b0 g
b0 f
b0 e
b0 d
b0 c
b0 b
bx a
bx `
b0 _
b0 ^
bx ]
bx \
bx [
bx Z
bx Y
bx X
1V
bx U
bx T
1R
bx Q
bx P
b0 O
bx N
bx M
b0 L
bx K
bx J
bx I
bx H
b0 G
bx F
bx E
0D
bx C
bx B
0A
0@
1?
bx >
b0 =
bx <
0;
bx :
bx 9
bx 8
bx 7
bx 6
05
04
x3
02
bx 1
bx 0
bx /
bx +
bx *
1)
0(
bx '
bx &
bx %
0$
0#
bx "
bx !
$end
#5000
b0 *
b0 K
b0 u
b100 J
b0 |
b0 '
b0 C
b0 T
b0 U
b0 &
b0 +
b0 B
b0 q
b0 E
b0 X
b0 "
b0 >
b0 I
b100000 {
b100000000000 &"
b100000000000 0
1(
#10000
0(
#12000
0)
#15000
b10000 H
b10000 M
bx F
bx P
bx Q
1w
0v
1z
0?
b10000 =
b10000 c
b10000 ^
b10000 k
b10000 d
b10000 j
14
b10 G
b10 O
b10 b
15
b10000 9
b10000 Z
b10000 s
b0 :
b0 [
b0 r
b1 6
b1 Y
b1 t
b0 `
b0 a
b10011 \
bx *
b1000000000000000010010011 !
b1000000000000000010010011 <
b1000000000000000010010011 ]
b1000000000000000010010011 %"
b1 L
bx &
bx +
bx B
bx q
bx '
bx C
bx T
bx U
1(
#20000
0(
#25000
03
b10000 F
b10000 P
b10000 Q
bx K
bx u
b0 7
b0 o
b0 y
b0 8
b0 N
b0 x
bx E
bx X
b10 L
1(
#30000
0(
#35000
b10 *
b11 L
b0 &
b0 +
b0 B
b0 q
b10000 '
b10000 C
b10000 T
b10000 U
1(
#40000
0(
#45000
b10000 K
b10000 u
12
b10000 E
b10000 X
b100 L
1(
#50000
0(
#55000
b1000 J
b1 |
02
b100 "
b100 >
b100 I
b0 L
1(
#60000
0(
#65000
b110000 F
b110000 P
b110000 Q
b110000 H
b110000 M
b10 6
b10 Y
b10 t
b1 `
0?
b10 G
b10 O
b10 b
b110000 =
b110000 c
b110000 ^
b110000 k
b110000 d
b110000 j
14
15
b1 L
b11000000000000000100010011 !
b11000000000000000100010011 <
b11000000000000000100010011 ]
b11000000000000000100010011 %"
1(
#70000
0(
#75000
b110 *
b10 L
b110000 '
b110000 C
b110000 T
b110000 U
1(
#80000
0(
#85000
b110000 K
b110000 u
b110000 E
b110000 X
b11 L
1(
#90000
0(
#95000
12
b100 L
1(
#100000
0(
#105000
b1100 J
b10 |
02
b1000 "
b1000 >
b1000 I
b0 L
1(
#110000
0(
#115000
13
1v
b0 F
b0 P
b0 Q
b0 H
b0 M
b1 9
b1 Z
b1 s
b10 :
b10 [
b10 r
b11 6
b11 Y
b11 t
b110000 `
b110011 \
0?
b110 G
b110 O
b110 b
b0 =
b0 c
b0 ^
b0 k
b0 d
b0 j
04
15
b1100000000100010000000110110011 !
b1100000000100010000000110110011 <
b1100000000100010000000110110011 ]
b1100000000100010000000110110011 %"
b1 L
1(
#120000
0(
#125000
03
b10000 H
b10000 M
b100000 F
b100000 P
b100000 Q
b0 *
b10000 7
b10000 o
b10000 y
b110000 8
b110000 N
b110000 x
b0 '
b0 C
b0 T
b0 U
b10 L
1(
#130000
0(
#135000
b0 K
b0 u
b100 *
b11 L
b0 E
b0 X
b10000 &
b10000 +
b10000 B
b10000 q
b100000 '
b100000 C
b100000 T
b100000 U
1(
#140000
0(
#145000
b100000 K
b100000 u
12
b100000 E
b100000 X
b100 L
1(
#150000
0(
#155000
b10000 J
b11 |
02
b1100 "
b1100 >
b1100 I
b0 L
1(
#160000
0(
#165000
b1000 H
b1000 M
1@
b1000 =
b1000 c
b1000 ^
b1000 k
b1000 d
b1000 j
14
b111000 F
b111000 P
b111000 Q
b11 9
b11 Z
b11 s
b1000 6
b1000 Y
b1000 t
b0 `
b11 a
b100011 \
0?
b10 G
b10 O
b10 b
05
b1 L
b1100010011010000100011 !
b1100010011010000100011 <
b1100010011010000100011 ]
b1100010011010000100011 %"
1(
#170000
0(
#175000
b111 *
b10 L
b111000 '
b111000 C
b111000 T
b111000 U
b100000 7
b100000 o
b100000 y
1(
#180000
0(
#185000
b111000 K
b111000 u
1#
b100000 &
b100000 +
b100000 B
b100000 q
b111000 E
b111000 X
b11 L
1(
#190000
0(
#195000
0#
b100 L
1(
#200000
0(
#205000
b10100 J
b100 |
b10000 "
b10000 >
b10000 I
b0 L
1(
#210000
0(
#215000
bx K
bx u
1;
1A
15
b1011000 F
b1011000 P
b1011000 Q
b101000 H
b101000 M
b1000 9
b1000 Z
b1000 s
b1 :
b1 [
b1 r
b100 6
b100 Y
b100 t
b1 `
b11 \
0?
0@
b10 G
b10 O
b10 b
b101000 =
b101000 c
b101000 ^
b101000 k
b101000 d
b101000 j
14
b10100000001011001000000011 !
b10100000001011001000000011 <
b10100000001011001000000011 ]
b10100000001011001000000011 %"
b1 L
1(
#220000
0(
#225000
b111000 F
b111000 P
b111000 Q
b1011 *
b0 7
b0 o
b0 y
b10000 8
b10000 N
b10000 x
b1011000 '
b1011000 C
b1011000 T
b1011000 U
b10 L
1(
#230000
0(
#235000
1$
b111 *
b11 L
b1011000 E
b1011000 X
b0 &
b0 +
b0 B
b0 q
b111000 '
b111000 C
b111000 T
b111000 U
1(
#240000
0(
#245000
12
0$
b100000 K
b100000 u
b111000 E
b111000 X
b100 L
b100000 %
b100000 /
b100000 1
1(
#250000
0(
#255000
b11000 J
b101 |
02
b10100 "
b10100 >
b10100 I
b0 L
1(
#260000
0(
#265000
b111000 K
b111000 u
0w
0v
b1111111111111111111111111111111111111111111111111111111111101100 _
b1111111111111111111111111111111111111111111111111111111111101100 g
b1111111101100 e
b1111111101100 f
1D
b10000 F
b10000 P
b10000 Q
b0 H
b0 M
b0 9
b0 Z
b0 s
b0 :
b0 [
b0 r
b1101 6
b1101 Y
b1101 t
b1111111 `
b0 a
b1100011 \
0?
0;
0A
b110 G
b110 O
b110 b
b1111111111111111111111111111111111111111111111111111111111101100 =
b1111111111111111111111111111111111111111111111111111111111101100 c
b0 ^
b0 k
b0 d
b0 j
04
05
b1 L
b11111110000000000000011011100011 !
b11111110000000000000011011100011 <
b11111110000000000000011011100011 ]
b11111110000000000000011011100011 %"
1(
#270000
0(
#275000
b0 J
13
b10 *
b0 F
b0 P
b0 Q
b10 L
b10000 '
b10000 C
b10000 T
b10000 U
b0 8
b0 N
b0 x
1(
#280000
0(
#285000
b0 *
b10000 K
b10000 u
b0 '
b0 C
b0 T
b0 U
b10000 E
b10000 X
b11 L
1(
#290000
0(
#295000
b0 K
b0 u
b100 L
b0 E
b0 X
1(
#300000
0(
#305000
b1111111111111111111111111111111111111111111111111111111111101100 J
b0 |
b0 "
b0 >
b0 I
b0 L
1(
#310000
0(
#315000
03
b10000 F
b10000 P
b10000 Q
b10000 H
b10000 M
1w
b10000 ^
b10000 k
b10000 d
b10000 j
14
15
b100 J
b10000 9
b10000 Z
b10000 s
b1 6
b1 Y
b1 t
b0 `
b10011 \
0?
0D
b10 G
b10 O
b10 b
b10000 =
b10000 c
b0 _
b0 g
b0 e
b0 f
b1000000000000000010010011 !
b1000000000000000010010011 <
b1000000000000000010010011 ]
b1000000000000000010010011 %"
b1 L
1(
#320000
0(
#325000
b10 *
b10000 '
b10000 C
b10000 T
b10000 U
b10 L
1(
#330000
0(
#335000
b10000 K
b10000 u
b11 L
b10000 E
b10000 X
1(
#340000
0(
#345000
12
b100 L
1(
#350000
0(
#355000
b1000 J
b1 |
02
b100 "
b100 >
b100 I
b0 L
1(
#360000
0(
#365000
b110000 F
b110000 P
b110000 Q
b110000 H
b110000 M
b10 6
b10 Y
b10 t
b1 `
0?
b10 G
b10 O
b10 b
b110000 =
b110000 c
b110000 ^
b110000 k
b110000 d
b110000 j
14
15
b1 L
b11000000000000000100010011 !
b11000000000000000100010011 <
b11000000000000000100010011 ]
b11000000000000000100010011 %"
1(
#370000
0(
#375000
b110 *
b10 L
b110000 '
b110000 C
b110000 T
b110000 U
1(
#380000
0(
#385000
b110000 K
b110000 u
b110000 E
b110000 X
b11 L
1(
#390000
0(
#395000
12
b100 L
1(
#400000
0(
#405000
b1100 J
b10 |
02
b1000 "
b1000 >
b1000 I
b0 L
1(
#410000
0(
#415000
13
1v
b0 F
b0 P
b0 Q
b0 H
b0 M
b1 9
b1 Z
b1 s
b10 :
b10 [
b10 r
b11 6
b11 Y
b11 t
b110000 `
b110011 \
0?
b110 G
b110 O
b110 b
b0 =
b0 c
b0 ^
b0 k
b0 d
b0 j
04
15
b1100000000100010000000110110011 !
b1100000000100010000000110110011 <
b1100000000100010000000110110011 ]
b1100000000100010000000110110011 %"
b1 L
1(
#420000
0(
#425000
03
b10000 H
b10000 M
b100000 F
b100000 P
b100000 Q
b0 *
b10000 7
b10000 o
b10000 y
b110000 8
b110000 N
b110000 x
b0 '
b0 C
b0 T
b0 U
b10 L
1(
#430000
0(
#435000
b0 K
b0 u
b100 *
b11 L
b0 E
b0 X
b10000 &
b10000 +
b10000 B
b10000 q
b100000 '
b100000 C
b100000 T
b100000 U
1(
#440000
0(
#445000
b100000 K
b100000 u
12
b100000 E
b100000 X
b100 L
1(
#450000
0(
#455000
b10000 J
b11 |
02
b1100 "
b1100 >
b1100 I
b0 L
1(
#460000
0(
#465000
b1000 H
b1000 M
1@
b1000 =
b1000 c
b1000 ^
b1000 k
b1000 d
b1000 j
14
b111000 F
b111000 P
b111000 Q
b11 9
b11 Z
b11 s
b1000 6
b1000 Y
b1000 t
b0 `
b11 a
b100011 \
0?
b10 G
b10 O
b10 b
05
b1 L
b1100010011010000100011 !
b1100010011010000100011 <
b1100010011010000100011 ]
b1100010011010000100011 %"
1(
#470000
0(
#475000
b111 *
b10 L
b111000 '
b111000 C
b111000 T
b111000 U
b100000 7
b100000 o
b100000 y
1(
#480000
0(
#485000
b111000 K
b111000 u
1#
b100000 &
b100000 +
b100000 B
b100000 q
b111000 E
b111000 X
b11 L
1(
#490000
0(
#495000
0#
b100 L
1(
#500000
0(
#505000
b10100 J
b100 |
b10000 "
b10000 >
b10000 I
b0 L
1(
#510000
0(
#515000
b100000 K
b100000 u
1;
1A
15
b1011000 F
b1011000 P
b1011000 Q
b101000 H
b101000 M
b1000 9
b1000 Z
b1000 s
b1 :
b1 [
b1 r
b100 6
b100 Y
b100 t
b1 `
b11 \
0?
0@
b10 G
b10 O
b10 b
b101000 =
b101000 c
b101000 ^
b101000 k
b101000 d
b101000 j
14
b10100000001011001000000011 !
b10100000001011001000000011 <
b10100000001011001000000011 ]
b10100000001011001000000011 %"
b1 L
1(
#520000
0(
#525000
b111000 F
b111000 P
b111000 Q
b1011 *
b0 7
b0 o
b0 y
b10000 8
b10000 N
b10000 x
b1011000 '
b1011000 C
b1011000 T
b1011000 U
b10 L
1(
#530000
0(
#535000
1$
b111 *
b11 L
b1011000 E
b1011000 X
b0 &
b0 +
b0 B
b0 q
b111000 '
b111000 C
b111000 T
b111000 U
1(
#540000
0(
#545000
12
0$
b111000 E
b111000 X
b100 L
1(
#550000
0(
