multicycle_subset/memory.sv
module synchronous_memory #(
    parameter ADDR_WIDTH = 12,
    parameter WORD_SIZE = 64
)(
    input logic clk,
    input logic reset,
    input logic read_enable,
    input logic write_enable,
    input logic [WORD_SIZE - 1 : 0] addr,
    input logic [WORD_SIZE - 1 : 0] write_data,
    output logic [WORD_SIZE - 1 : 0] read_data
);

localparam NUM_WORDS = 1 << ADDR_WIDTH;
logic [WORD_SIZE - 1 : 0] memory [0 : NUM_WORDS - 1];

integer i;
always_ff @(posedge clk) begin
    if (reset) begin
        for (i = 0; i < 1 << ADDR_WIDTH - 1; i = i + 1) begin
            memory[i] <= {{WORD_SIZE}{1'b0}};
        end
    end
    
    else begin
        if (write_enable) begin
            memory[addr] <= write_data;
        end
        if (read_enable) begin
            read_data <= memory[addr];
        end
    end
end

endmodule

multicycle_subset/registers.sv
module riscv_regfile (
    input logic clk,
    input logic reset,
    input logic write_enable,
    input logic [63:0] write_data,
    input logic [4:0] write_addr,
    input logic [4:0] read_addr1,
    input logic [4:0] read_addr2,
    output logic [63:0] read_port1,
    output logic [63:0] read_port2
);

logic [63:0] data [0:31];
logic write_addr_nonzero, read_addr1_nonzero, read_addr2_nonzero;

always_comb begin
    write_addr_nonzero = |write_addr;
    read_addr1_nonzero = |read_addr1;
    read_addr2_nonzero = |read_addr2;
end

integer i;

always_ff @(posedge clk) begin
    if (reset) begin
        for (i = 0; i < 32; i = i + 1) begin
            data[i] <= 64'b0;
        end
    end
    else begin
        if (write_enable && write_addr_nonzero) begin
            data[write_addr] <= write_data;
        end

        read_port1 <= data[read_addr1] & {64{read_addr1_nonzero}};
        read_port2 <= data[read_addr2] & {64{read_addr2_nonzero}};
    end
end

endmodule

module packed_dff #(
    parameter WORD_SIZE = 64
)(
    input logic clk,
    input logic reset,
    input logic write_enable,
    input logic [WORD_SIZE - 1 : 0] write_data,
    output logic [WORD_SIZE - 1 : 0] stored_data
);

always_ff @(posedge clk) begin
    if (reset) begin
        stored_data <= {(WORD_SIZE){1'b0}};
    end
    else if (write_enable) begin
        stored_data <= write_data;
    end
end

endmodule

pipeline/alu.sv
module alu_64 (
    input logic [63:0] operand_1,
    input logic [63:0] operand_2,
    input logic [3:0] opcode,
    output logic [63:0] result,
    output logic zero_flag
);

assign zero_flag = ~(|result);

always_comb begin
    result = 64'b0;

    case (opcode)
        4'b0000:
            result = operand_1 & operand_2;
        4'b0001:
            result = operand_1 | operand_2;
        4'b0010:
            result = operand_1 + operand_2;
        4'b0110:
            result = operand_1 - operand_2;
    endcase
end

endmodule

multicycle_subset/control.sv
module imm_sign_extend #(
    parameter IMM_WIDTH_IN = 12,
    parameter IMM_WIDTH_OUT = 64
)(
    input logic [IMM_WIDTH_IN - 1 : 0] imm_in,
    output logic [IMM_WIDTH_OUT - 1 : 0] imm_out
);

assign imm_out = {
    {(IMM_WIDTH_OUT - IMM_WIDTH_IN){imm_in[IMM_WIDTH_IN - 1]}}, 
    imm_in};

endmodule

module riscv_subset_decoder (
    input logic [31:0] instr,
    output logic reg_write,
    output logic [4:0] reg_waddr,
    output logic [4:0] reg_raddr1,
    output logic [4:0] reg_raddr2,
    output logic use_imm_in_alu,
    output logic [63:0] imm,
    output logic [3:0] alu_opcode,
    output logic dmem_read,
    output logic dmem_write,
    output logic load_instr,
    output logic branch,
    output logic illegal
);

logic [6:0] opcode;
logic [2:0] funct3;
logic [6:0] funct7;

assign opcode = instr[6:0];
assign funct3 = instr[14:12];
assign funct7 = instr[31:25];

logic [11:0] imm12;
logic [12:0] imm13;
logic [63:0] imm_mem;
logic [63:0] imm_b;

imm_sign_extend #(
    .IMM_WIDTH_IN(12),
    .IMM_WIDTH_OUT(64)
) imm_extender_mem (
    .imm_in(imm12),
    .imm_out(imm_mem)
);

imm_sign_extend #(
    .IMM_WIDTH_IN(13),
    .IMM_WIDTH_OUT(64)
) imm_extender_b (
    .imm_in(imm13),
    .imm_out(imm_b)
);

assign reg_waddr = instr[11:7];
assign reg_raddr1 = instr[19:15];
assign reg_raddr2 = instr[24:20];

always_comb begin
    reg_write = 1'b0;
    use_imm_in_alu = 1'b0;
    imm12 = 12'b0;
    imm13 = 13'b0;
    imm = 64'b0;
    alu_opcode = 4'b0;
    dmem_read = 1'b0;
    dmem_write = 1'b0;
    load_instr = 1'b0;
    branch = 1'b0;
    illegal = 1'b1;

    case (opcode)
        //ld
        7'b0000011: begin
            if (funct3 == 3'b011) begin
                reg_write = 1'b1;
                use_imm_in_alu = 1'b1;
                imm12 = instr[31:20];
                imm = imm_mem;
                alu_opcode = 4'b0010;
                dmem_read = 1'b1;
                load_instr = 1'b1;
                illegal = 1'b0;
            end
        end
        //sd
        7'b0100011: begin
            if (funct3 == 3'b011) begin
                use_imm_in_alu = 1'b1;
                imm12 = {instr[31:25], instr[11:7]};
                imm = imm_mem;
                alu_opcode = 4'b0010;
                dmem_write = 1'b1;
                illegal = 1'b0;
            end
        end
        //beq
        7'b1100011: begin
            if (funct3 == 3'b000) begin
                alu_opcode = 4'b0110;
                branch = 1'b1;
                imm13 = {
                    instr[31],
                    instr[7],
                    instr[30:25],
                    instr[11:8],
                    1'b0
                };
                imm = imm_b;
                illegal = 1'b0;
            end
        end
        //arith: and, or, add, sub
        7'b0110011: begin
            case ({funct7, funct3})
                10'b0000000111: begin
                    reg_write = 1'b1;
                    alu_opcode = 4'b0;
                    illegal = 1'b0;
                end
                10'b0000000110: begin
                    reg_write = 1'b1;
                    alu_opcode = 4'b0001;
                    illegal = 1'b0;
                end
                10'b0000000000: begin
                    reg_write = 1'b1;
                    alu_opcode = 4'b0010;
                    illegal = 1'b0;
                end
                10'b0100000000: begin
                    reg_write = 1'b1;
                    alu_opcode = 4'b0110;
                    illegal = 1'b0;
                end
            endcase
        end
    endcase
end

endmodule

multicycle_subset/core.sv
module riscv64_subset_core_multicycle (
    input logic clk,
    input logic reset,
    input logic [31:0] instr, // Loaded on IF -> ID edge
    output logic [63:0] imem_addr,
    input logic [63:0] dmem_fetch, // A synchronized data memory module will load the correct value of data memory on an ld instruction on EX -> MEM edge.
    output logic dmem_read,
    output logic dmem_write,
    output logic [63:0] dmem_addr,
    output logic [63:0] dmem_data
);

enum {
    IF, ID, EX, MEM, WB
} processor_state;

// ID phase

logic reg_write_dec;
logic [4:0] reg_waddr;
logic [4:0] reg_raddr1;
logic [4:0] reg_raddr2;
logic use_imm_in_alu;
logic [63:0] imm;
logic [3:0] alu_opcode;
logic dmem_read_dec;
logic dmem_write_dec;
logic load_instr;
logic branch;
logic illegal;

riscv_subset_decoder instr_decoder (
    .instr(instr),
    .reg_write(reg_write_dec),
    .reg_waddr(reg_waddr),
    .reg_raddr1(reg_raddr1),
    .reg_raddr2(reg_raddr2),
    .use_imm_in_alu(use_imm_in_alu),
    .imm(imm),
    .alu_opcode(alu_opcode),
    .dmem_read(dmem_read_dec),
    .dmem_write(dmem_write_dec),
    .load_instr(load_instr),
    .branch(branch),
    .illegal(illegal)
);

logic reg_write;
assign reg_write = reg_write_dec & (processor_state == WB);
assign dmem_read = dmem_read_dec & (processor_state == MEM);
assign dmem_write = dmem_write_dec & (processor_state == MEM);

logic [63:0] reg_wdata;
logic [63:0] reg_rdata1;
logic [63:0] reg_rdata2; // Loaded on ID -> EX edge
logic [63:0] alu_input2;

// ID/EX

riscv_regfile regfile (
    .clk(clk),
    .reset(reset),
    .write_enable(reg_write),
    .write_data(reg_wdata),
    .write_addr(reg_waddr),
    .read_addr1(reg_raddr1),
    .read_addr2(reg_raddr2),
    .read_port1(reg_rdata1), // Regfile output ports
    .read_port2(reg_rdata2)
);

// EX phase

logic zero_flag; // Used for branching
logic [63:0] alu_result;

always_comb begin
    if (use_imm_in_alu)
        alu_input2 = imm;
    else
        alu_input2 = reg_rdata2;
end

alu_64 alu (
    .operand_1(reg_rdata1),
    .operand_2(alu_input2),
    .opcode(alu_opcode),
    .result(alu_result),
    .zero_flag(zero_flag)
);

// EX/MEM

packed_dff #(
    .WORD_SIZE(64)
) alu_result_dff_ex_mem (
    .clk(clk),
    .reset(reset),
    .write_enable(1'b1),
    .write_data(alu_result),
    .stored_data(dmem_addr)
);

packed_dff #(
    .WORD_SIZE(64)
) reg_rdata2_dff_ex_mem (
    .clk(clk),
    .reset(reset),
    .write_enable(1'b1),
    .write_data(reg_rdata2),
    .stored_data(dmem_data)
);

// MEM will be handled by the external memory module.

// MEM/WB

logic [63:0] alu_result_wb;

packed_dff #(
    .WORD_SIZE(64)
) alu_result_dff_mem_wb (
    .clk(clk),
    .reset(reset),
    .write_enable(1'b1),
    .write_data(dmem_addr),
    .stored_data(alu_result_wb)
);

// WB phase
always_comb begin
    if (load_instr)
        reg_wdata = dmem_fetch;
    else
        reg_wdata = alu_result_wb;
end

logic [63:0] instr_addr; // PC will update on WB -> IF edge.
logic [63:0] next_instr_addr;
assign imem_addr = instr_addr;

always_comb begin
    if (branch & zero_flag)
        next_instr_addr = instr_addr + imm;
    else
        next_instr_addr = instr_addr + 64'd4;
end

always_ff @(posedge clk) begin
    if (reset) begin
        processor_state <= IF;
        instr_addr <= 64'b0;
    end
    else begin
        case (processor_state)
            IF: processor_state <= ID;
            ID: processor_state <= EX;
            EX: processor_state <= MEM;
            MEM: processor_state <= WB;
            WB: begin
                processor_state <= IF;
                instr_addr <= next_instr_addr;
            end
        endcase
    end
end

endmodule

multicycle_subset/core_tb.sv
`timescale 1ns/1ps

module riscv64_subset_core_multicycle_tb;

logic clk;
logic reset;

logic [31:0] instr;
logic [63:0] imem_addr;

logic [63:0] dmem_fetch;
logic        dmem_read;
logic        dmem_write;
logic [63:0] dmem_addr;
logic [63:0] dmem_data;

riscv64_subset_core_multicycle dut (
    .clk        (clk),
    .reset      (reset),

    .instr      (instr),
    .imem_addr  (imem_addr),

    .dmem_fetch (dmem_fetch),
    .dmem_read  (dmem_read),
    .dmem_write (dmem_write),
    .dmem_addr  (dmem_addr),
    .dmem_data  (dmem_data)
);

synchronous_memory #(
    .ADDR_WIDTH(12),
    .WORD_SIZE(32)
) instr_memory (
    .clk(clk),
    .reset(reset),
    .read_enable(1'b1),
    .write_enable(1'b0),
    .addr(imem_addr[13:2]),
    .write_data(32'b0),
    .read_data(instr)
);

synchronous_memory #(
    .ADDR_WIDTH(12),
    .WORD_SIZE(64)
) data_memory (
    .clk(clk),
    .reset(reset),
    .read_enable(dmem_read),
    .write_enable(dmem_write),
    .addr(dmem_addr[14:3]),
    .write_data(dmem_data),
    .read_data(dmem_fetch)
);

initial begin
    clk = 1'b0;

    forever begin
        #5;
        clk = ~clk;
    end
end

initial begin
    $dumpfile("dump.vcd");
    $dumpvars(0, riscv64_subset_core_multicycle_tb);
end

initial begin
    reset = 1'b1;
    #12;
    reset = 1'b0;
end

initial begin
    // addi x1, x0, 16
    #13;
    instr_memory.memory[0] = {
        12'b000000010000,
        5'b00000,
        3'b000,
        5'b00001,
        7'b0010011
    };

    // addi x2, x0, 48
    instr_memory.memory[1] = {
        12'b000000110000,
        5'b00000,
        3'b000,
        5'b00010,
        7'b0010011
    };

    // sub x3, x2, x1
    instr_memory.memory[2] = {
        7'b0110000,
        5'b00001,
        5'b00010,
        3'b000,
        5'b00011,
        7'b0110011
    };

    // sd x3, 8(x2)
    instr_memory.memory[3] = {
        7'b0000000,
        5'b00011,
        5'b00010,
        3'b011,
        5'b01000,
        7'b0100011
    };

    // ld, x4, 40(x1)
    instr_memory.memory[4] = {
        12'b000000101000,
        5'b00001,
        3'b011,
        5'b00100,
        7'b0000011
    };

    // beq x0, x0, -20
    instr_memory.memory[5] = {
        7'b1111111,
        5'b00000,
        5'b00000,
        3'b000,
        5'b01101,
        7'b1100011
    };
end

always @(posedge clk) begin
    $display(
        "time=%0t PC=%0d state=%0d x1=%0d x2=%0d x3=%0d x4=%0d ALU=%0d",
        $time,
        imem_addr,
        dut.processor_state,
        dut.regfile.data[1],
        dut.regfile.data[2],
        dut.regfile.data[3],
        dut.regfile.data[4],
        dut.alu_result
    );
end

initial begin
    repeat (150) @(posedge clk);
    #1;
    $finish;
end

endmodule

multicycle_subset/dump.vcd
$date
	Thu Sep  3 10:36:46 2026
$end
$version
	Icarus Verilog
$end
$timescale
	1ps
$end
$scope module riscv64_subset_core_multicycle_tb $end
$var wire 64 ! imem_addr [63:0] $end
$var wire 1 " dmem_write $end
$var wire 1 # dmem_read $end
$var wire 64 $ dmem_data [63:0] $end
$var wire 64 % dmem_addr [63:0] $end
$var reg 1 & clk $end
$var reg 64 ' dmem_fetch [63:0] $end
$var reg 32 ( instr [31:0] $end
$var reg 1 ) reset $end
$scope module dut $end
$var wire 1 & clk $end
$var wire 64 * dmem_fetch [63:0] $end
$var wire 1 # dmem_read $end
$var wire 1 " dmem_write $end
$var wire 64 + imem_addr [63:0] $end
$var wire 32 , instr [31:0] $end
$var wire 1 - reg_write $end
$var wire 1 ) reset $end
$var wire 1 . zero_flag $end
$var wire 1 / use_imm_in_alu $end
$var wire 1 0 reg_write_dec $end
$var wire 5 1 reg_waddr [4:0] $end
$var wire 64 2 reg_rdata2 [63:0] $end
$var wire 64 3 reg_rdata1 [63:0] $end
$var wire 5 4 reg_raddr2 [4:0] $end
$var wire 5 5 reg_raddr1 [4:0] $end
$var wire 1 6 load_instr $end
$var wire 64 7 imm [63:0] $end
$var wire 1 8 illegal $end
$var wire 1 9 dmem_write_dec $end
$var wire 1 : dmem_read_dec $end
$var wire 64 ; dmem_data [63:0] $end
$var wire 64 < dmem_addr [63:0] $end
$var wire 1 = branch $end
$var wire 64 > alu_result_wb [63:0] $end
$var wire 64 ? alu_result [63:0] $end
$var wire 4 @ alu_opcode [3:0] $end
$var reg 64 A alu_input2 [63:0] $end
$var reg 64 B instr_addr [63:0] $end
$var reg 64 C next_instr_addr [63:0] $end
$var reg 64 D reg_wdata [63:0] $end
$var integer 32 E processor_state [31:0] $end
$scope module alu $end
$var wire 64 F operand_2 [63:0] $end
$var wire 1 . zero_flag $end
$var wire 64 G operand_1 [63:0] $end
$var wire 4 H opcode [3:0] $end
$var reg 64 I result [63:0] $end
$upscope $end
$scope module alu_result_dff_ex_mem $end
$var wire 1 & clk $end
$var wire 1 ) reset $end
$var wire 64 J write_data [63:0] $end
$var wire 1 K write_enable $end
$var parameter 32 L WORD_SIZE $end
$var reg 64 M stored_data [63:0] $end
$upscope $end
$scope module alu_result_dff_mem_wb $end
$var wire 1 & clk $end
$var wire 1 ) reset $end
$var wire 64 N write_data [63:0] $end
$var wire 1 O write_enable $end
$var parameter 32 P WORD_SIZE $end
$var reg 64 Q stored_data [63:0] $end
$upscope $end
$scope module instr_decoder $end
$var wire 32 R instr [31:0] $end
$var wire 5 S reg_waddr [4:0] $end
$var wire 5 T reg_raddr2 [4:0] $end
$var wire 5 U reg_raddr1 [4:0] $end
$var wire 7 V opcode [6:0] $end
$var wire 64 W imm_mem [63:0] $end
$var wire 64 X imm_b [63:0] $end
$var wire 7 Y funct7 [6:0] $end
$var wire 3 Z funct3 [2:0] $end
$var reg 4 [ alu_opcode [3:0] $end
$var reg 1 = branch $end
$var reg 1 : dmem_read $end
$var reg 1 9 dmem_write $end
$var reg 1 8 illegal $end
$var reg 64 \ imm [63:0] $end
$var reg 12 ] imm12 [11:0] $end
$var reg 13 ^ imm13 [12:0] $end
$var reg 1 6 load_instr $end
$var reg 1 0 reg_write $end
$var reg 1 / use_imm_in_alu $end
$scope module imm_extender_b $end
$var wire 13 _ imm_in [12:0] $end
$var wire 64 ` imm_out [63:0] $end
$var parameter 32 a IMM_WIDTH_IN $end
$var parameter 32 b IMM_WIDTH_OUT $end
$upscope $end
$scope module imm_extender_mem $end
$var wire 12 c imm_in [11:0] $end
$var wire 64 d imm_out [63:0] $end
$var parameter 32 e IMM_WIDTH_IN $end
$var parameter 32 f IMM_WIDTH_OUT $end
$upscope $end
$upscope $end
$scope module reg_rdata2_dff_ex_mem $end
$var wire 1 & clk $end
$var wire 1 ) reset $end
$var wire 1 g write_enable $end
$var wire 64 h write_data [63:0] $end
$var parameter 32 i WORD_SIZE $end
$var reg 64 j stored_data [63:0] $end
$upscope $end
$scope module regfile $end
$var wire 1 & clk $end
$var wire 5 k read_addr1 [4:0] $end
$var wire 5 l read_addr2 [4:0] $end
$var wire 1 ) reset $end
$var wire 5 m write_addr [4:0] $end
$var wire 64 n write_data [63:0] $end
$var wire 1 - write_enable $end
$var reg 1 o read_addr1_nonzero $end
$var reg 1 p read_addr2_nonzero $end
$var reg 64 q read_port1 [63:0] $end
$var reg 64 r read_port2 [63:0] $end
$var reg 1 s write_addr_nonzero $end
$var integer 32 t i [31:0] $end
$upscope $end
$upscope $end
$upscope $end
$enddefinitions $end
$comment Show the parameter values. $end
$dumpall
b1000000 i
b1000000 f
b1100 e
b1000000 b
b1101 a
b1000000 P
b1000000 L
$end
#0
$dumpvars
bx t
0s
bx r
bx q
0p
0o
bx n
b0 m
b0 l
b0 k
bx j
bx h
1g
b0 d
b0 c
b0 `
b0 _
b0 ^
b0 ]
b0 \
b0 [
b0 Z
b0 Y
b0 X
b0 W
b0 V
b0 U
b0 T
b0 S
b0 R
bx Q
1O
bx N
bx M
1K
bx J
bx I
b0 H
bx G
bx F
b0 E
bx D
bx C
bx B
bx A
b0 @
bx ?
bx >
0=
bx <
bx ;
0:
09
18
b0 7
06
b0 5
b0 4
bx 3
bx 2
b0 1
00
0/
x.
0-
b0 ,
bx +
b0 *
1)
b0 (
b0 '
0&
bx %
bx $
0#
0"
bx !
$end
#5000
b0 D
b0 n
b100 C
b0 %
b0 <
b0 M
b0 N
b0 $
b0 ;
b0 j
b0 >
b0 Q
b0 !
b0 +
b0 B
b100000 t
1&
#10000
0&
#12000
bx ?
bx I
bx J
1p
1o
1s
08
b10 @
b10 H
b10 [
10
b110011 V
b11 1
b11 S
b11 m
b1 5
b1 U
b1 k
b10 4
b10 T
b10 l
b1000001000000110110011 (
b1000001000000110110011 ,
b1000001000000110110011 R
0)
#15000
0.
b10100 A
b10100 F
b11110 ?
b11110 I
b11110 J
b1 E
bx $
bx ;
bx j
bx %
bx <
bx M
bx N
b10100 2
b10100 h
b10100 r
b1010 3
b1010 G
b1010 q
1&
#20000
0&
#25000
bx D
bx n
b11110 %
b11110 <
b11110 M
b11110 N
b10100 $
b10100 ;
b10100 j
bx >
bx Q
b10 E
1&
#30000
0&
#35000
b11110 D
b11110 n
b11 E
b11110 >
b11110 Q
1&
#40000
0&
#45000
1-
b100 E
1&
#50000
0&
#55000
b1000 C
0-
b100 !
b100 +
b100 B
b0 E
1&
#60000
0&
#65000
b1 E
1&
